bounded_pool_executor/__init__.py
bounded_pool_executor-0.0.3.dist-info/LICENSE
bounded_pool_executor-0.0.3.dist-info/METADATA
bounded_pool_executor-0.0.3.dist-info/WHEEL
bounded_pool_executor-0.0.3.dist-info/top_level.txt
bounded_pool_executor-0.0.3.dist-info/RECORD
