Metadata-Version: 2.1
Name: bounded_pool_executor
Version: 0.0.3
Summary: Bounded Process&Thread Pool Executor
Home-page: http://github.com/mowshon/bounded_pool_executor
Author: Mowshon
Author-email: mowshon@yandex.ru
License: MIT
Keywords: concurrent futures ProcessPoolExecutor ThreadPoolExecutor Semaphore memory leak
Platform: UNKNOWN
Classifier: Programming Language :: Python :: 3
Classifier: License :: OSI Approved :: MIT License
Classifier: Operating System :: OS Independent
